asynapplicationinsights/__init__.py
asynapplicationinsights/aiohttp.py
asynapplicationinsights/entities.py
asynapplicationinsights/exceptions.py
asynapplicationinsights/telemetry.py
asynapplicationinsights/channel/__init__.py
asynapplicationinsights/channel/abstractions.py
asynapplicationinsights/channel/aiohttpchannel.py
asynapplicationinsights/tests/__init__.py
asynapplicationinsights/tests/settings.py
asynapplicationinsights/tests/test_ai.py
asynapplicationinsights/tests/test_entities.py
asynapplicationinsights/utils/__init__.py
asynapplicationinsights/utils/json.py
asynapplicationinsights-0.0.4.dist-info/LICENSE
asynapplicationinsights-0.0.4.dist-info/METADATA
asynapplicationinsights-0.0.4.dist-info/WHEEL
asynapplicationinsights-0.0.4.dist-info/top_level.txt
asynapplicationinsights-0.0.4.dist-info/RECORD
