Metadata-Version: 2.1
Name: asynapplicationinsights
Version: 0.0.4
Summary: Azure Application Insights client using asyncio
Home-page: https://github.com/RobertoPrevato/asynapplicationinsights
Author: Roberto Prevato
Author-email: roberto.prevato@gmail.com
License: MIT
Keywords: asyncio aiohttp azure application insights telemetry
Platform: UNKNOWN
Classifier: Development Status :: 3 - Alpha
Classifier: License :: OSI Approved :: MIT License
Classifier: Programming Language :: Python :: 3.6
Classifier: Operating System :: OS Independent
Classifier: Framework :: AsyncIO
Requires-Dist: aiohttp
